language/__init__.py
language/ast_1.py
language/enviroment.py
language/errors.py
language/exceptions.py
language/function.py
language/interpreter.py
language/lexer.py
language/parser.py
language/tokentype.py
language/tokn.py
lnkdnlng/__init__.py
lnkdnlng/main.py
lnkdnlng-1.0.0.dist-info/licenses/LICENSE
lnkdnlng-1.0.0.dist-info/METADATA
lnkdnlng-1.0.0.dist-info/WHEEL
lnkdnlng-1.0.0.dist-info/entry_points.txt
lnkdnlng-1.0.0.dist-info/top_level.txt
lnkdnlng-1.0.0.dist-info/RECORD
