Metadata-Version: 2.4
Name: lnkdnlng
Version: 1.0.0
Summary: A cli interpreter for LinkedInLanguage.
Author: whirlxd
Author-email: lnkdnlng@whirlxd.dev
Classifier: Programming Language :: Python :: 3
Classifier: Operating System :: OS Independent
Requires-Python: >=3.6
License-File: LICENSE
Dynamic: author
Dynamic: author-email
Dynamic: classifier
Dynamic: license-file
Dynamic: requires-python
Dynamic: summary
